{
  "lacma": {
    "zero_streak": 0,
    "last_success": "2026-07-09"
  },
  "hammer": {
    "zero_streak": 0,
    "last_success": "2026-07-09"
  },
  "moca_grand": {
    "zero_streak": 0,
    "last_success": "2026-07-09"
  },
  "the_broad": {
    "zero_streak": 0,
    "last_success": "2026-07-09"
  },
  "getty_center": {
    "zero_streak": 15,
    "last_success": "2026-06-24"
  },
  "norton_simon": {
    "zero_streak": 0,
    "last_success": "2026-07-09"
  },
  "huntington": {
    "zero_streak": 0,
    "last_success": "2026-07-09"
  },
  "self_help_graphics": {
    "zero_streak": 0,
    "last_success": "2026-07-09"
  },
  "craft_contemporary": {
    "zero_streak": 0,
    "last_success": "2026-07-09"
  },
  "redcat": {
    "zero_streak": 0,
    "last_success": "2026-07-09"
  },
  "ica_la": {
    "zero_streak": 0,
    "last_success": "2026-07-09"
  },
  "lace": {
    "zero_streak": 0,
    "last_success": "2026-07-09"
  },
  "18th_street": {
    "zero_streak": 0,
    "last_success": "2026-07-09"
  },
  "human_resources": {
    "zero_streak": 0,
    "last_success": "2026-07-09"
  },
  "wende": {
    "zero_streak": 0,
    "last_success": "2026-07-09"
  },
  "vincent_price": {
    "zero_streak": 0,
    "last_success": "2026-07-09"
  },
  "pvac": {
    "zero_streak": 0,
    "last_success": "2026-07-09"
  },
  "molaa": {
    "zero_streak": 0,
    "last_success": "2026-07-09"
  },
  "mak_center": {
    "zero_streak": 0,
    "last_success": "2026-07-09"
  },
  "marciano": {
    "zero_streak": 0,
    "last_success": "2026-07-09"
  },
  "armory_pasadena": {
    "zero_streak": 0,
    "last_success": "2026-07-09"
  },
  "janm": {
    "zero_streak": 0,
    "last_success": "2026-07-09"
  },
  "autry": {
    "zero_streak": 0,
    "last_success": "2026-07-09"
  },
  "fowler": {
    "zero_streak": 0,
    "last_success": "2026-07-09"
  },
  "academy_museum": {
    "zero_streak": 0,
    "last_success": "2026-07-09"
  },
  "usc_fisher": {
    "zero_streak": 0,
    "last_success": "2026-07-09"
  },
  "angels_gate": {
    "zero_streak": 0,
    "last_success": "2026-07-09"
  },
  "avenue_50": {
    "zero_streak": 0,
    "last_success": "2026-07-09"
  },
  "las_fotos_project": {
    "zero_streak": 0,
    "last_success": "2026-07-09"
  },
  "lbma": {
    "zero_streak": 0,
    "last_success": "2026-07-09"
  },
  "joan": {
    "zero_streak": 0,
    "last_success": "2026-07-09"
  },
  "moca_geffen": {
    "zero_streak": 0,
    "last_success": "2026-07-09"
  },
  "skirball": {
    "zero_streak": 0,
    "last_success": "2026-07-09"
  },
  "benton": {
    "zero_streak": 0,
    "last_success": "2026-07-09"
  },
  "torrance_art_museum": {
    "zero_streak": 0,
    "last_success": "2026-07-09"
  },
  "forest_lawn": {
    "zero_streak": 0,
    "last_success": "2026-07-09"
  },
  "brand_library": {
    "zero_streak": 0,
    "last_success": "2026-07-09"
  },
  "pieter": {
    "zero_streak": 0,
    "last_success": "2026-07-09"
  },
  "museum_of_tolerance": {
    "zero_streak": 0,
    "last_success": "2026-07-09"
  },
  "pacific_asia_museum": {
    "zero_streak": 0,
    "last_success": "2026-07-09"
  },
  "art_practice": {
    "zero_streak": 0,
    "last_success": "2026-07-09"
  },
  "calarts": {
    "zero_streak": 19,
    "last_success": "2026-06-20"
  },
  "lamag": {
    "zero_streak": 20,
    "last_success": "2026-06-19"
  },
  "sciarc": {
    "zero_streak": 0,
    "last_success": "2026-07-09"
  },
  "sparc": {
    "zero_streak": 0,
    "last_success": "2026-07-09"
  },
  "beyond_baroque": {
    "zero_streak": 0,
    "last_success": "2026-07-09"
  },
  "corita_art_center": {
    "zero_streak": 0,
    "last_success": "2026-07-09"
  },
  "la_plaza": {
    "zero_streak": 0,
    "last_success": "2026-07-09"
  },
  "clockshop": {
    "zero_streak": 0,
    "last_success": "2026-07-09"
  }
}
